fastapi_users/__init__.py
fastapi_users/exceptions.py
fastapi_users/fastapi_users.py
fastapi_users/jwt.py
fastapi_users/manager.py
fastapi_users/models.py
fastapi_users/openapi.py
fastapi_users/password.py
fastapi_users/py.typed
fastapi_users/schemas.py
fastapi_users/types.py
fastapi_users/authentication/__init__.py
fastapi_users/authentication/authenticator.py
fastapi_users/authentication/backend.py
fastapi_users/authentication/strategy/__init__.py
fastapi_users/authentication/strategy/base.py
fastapi_users/authentication/strategy/jwt.py
fastapi_users/authentication/strategy/redis.py
fastapi_users/authentication/strategy/db/__init__.py
fastapi_users/authentication/strategy/db/adapter.py
fastapi_users/authentication/strategy/db/models.py
fastapi_users/authentication/strategy/db/strategy.py
fastapi_users/authentication/transport/__init__.py
fastapi_users/authentication/transport/base.py
fastapi_users/authentication/transport/bearer.py
fastapi_users/authentication/transport/cookie.py
fastapi_users/db/__init__.py
fastapi_users/db/base.py
fastapi_users/router/__init__.py
fastapi_users/router/auth.py
fastapi_users/router/common.py
fastapi_users/router/oauth.py
fastapi_users/router/register.py
fastapi_users/router/reset.py
fastapi_users/router/users.py
fastapi_users/router/verify.py
fastapi_users-15.0.2.dist-info/METADATA
fastapi_users-15.0.2.dist-info/WHEEL
fastapi_users-15.0.2.dist-info/licenses/LICENSE
fastapi_users-15.0.2.dist-info/RECORD
